remotecv_multidir/__init__.py
remotecv_multidir/_version.py
remotecv_multidir/loader.py
remotecv_redis/__init__.py
remotecv_redis/loader.py
remotecv_multidir-0.1.1.dist-info/LICENSE
remotecv_multidir-0.1.1.dist-info/METADATA
remotecv_multidir-0.1.1.dist-info/WHEEL
remotecv_multidir-0.1.1.dist-info/top_level.txt
remotecv_multidir-0.1.1.dist-info/RECORD
