Metadata-Version: 2.1
Name: remotecv-multidir
Version: 0.1.1
Summary: RemoteCV image loader from multiple local directories
Home-page: https://github.com/benneic/remotecv_multidir
Author: Benn Eichhorn
Author-email: beichhor@gmail.com
License: MIT
Keywords: imaging face detection feature opencv multidir thumbor storage loader
Platform: UNKNOWN
Classifier: Development Status :: 4 - Beta
Classifier: Intended Audience :: Developers
Classifier: License :: OSI Approved :: MIT License
Classifier: Natural Language :: English
Classifier: Operating System :: MacOS
Classifier: Operating System :: POSIX :: Linux
Classifier: Programming Language :: Python :: 2.6
Classifier: Topic :: Internet :: WWW/HTTP :: Dynamic Content
Classifier: Topic :: Multimedia :: Graphics :: Presentation
Requires-Dist: derpconf
